LICENSE.txt
MANIFEST.in
README.md
setup.cfg
setup.py
OnloadExcel.egg-info/PKG-INFO
OnloadExcel.egg-info/SOURCES.txt
OnloadExcel.egg-info/dependency_links.txt
OnloadExcel.egg-info/top_level.txt
OnloadTable/__init__.py
OnloadTable/onload.py
OnloadTable/Function/__init__.py
OnloadTable/Function/mysqlexcel.py
OnloadTable/Function/optionDb.py
OnloadTable/Function/settings.py
OnloadTable/Function/Function/__init__.py
OnloadTable/Function/Ui/ExcelUi.py
OnloadTable/Function/Ui/MaskWin.py
OnloadTable/Function/Ui/__init__.py
OnloadTable/Ui/__init__.py
OnloadTable/Ui/onloadUi.py