Metadata-Version: 2.1
Name: OnloadExcel
Version: 0.1.2
Summary: 上传底稿目录功能
Home-page: https://mail.163.com/js6/main.jsp?sid=PAlGWIYldfIQjfQTFYllFVEyKXidwtNk&df=mail163_letter#module=welcome.WelcomeModule%7C%7B%7D
Author: wangweidong
Author-email: 17891967090@163.com
Classifier: Programming Language :: Python
Requires-Python: >=3.8
License-File: LICENSE.txt
